APIDocTest-0.0.3.data/data/APIDocTestV0.0.3.jpg
APIDocTest-0.0.3.data/data/examples/with-flask.py
apidoctest/__init__.py
apidoctest/apidoctest.py
apidoctest/static/apidoctest.css
apidoctest/static/apidoctest.js
apidoctest/templates/apidoctest.html
APIDocTest-0.0.3.dist-info/LICENSE
APIDocTest-0.0.3.dist-info/METADATA
APIDocTest-0.0.3.dist-info/WHEEL
APIDocTest-0.0.3.dist-info/top_level.txt
APIDocTest-0.0.3.dist-info/RECORD
