Metadata-Version: 2.1
Name: APIDocTest
Version: 0.0.3
Summary: A lightweight Python WebAPI's documents and tests framework based on __doc__, VanillaJS-AJAX and Flask, but not limited to Flask.
Home-page: https://github.com/nagexiucai/APIDocTest
Author: bob-nx
Author-email: me@nagexiucai.com
License: UNKNOWN
Keywords: pip,apidoc,test,api,document,flask
Platform: UNKNOWN
Classifier: Programming Language :: Python :: 2 :: Only
Classifier: License :: OSI Approved :: MIT License
Classifier: Operating System :: OS Independent
Requires-Python: >=2.6, <3
